setup.py
APNNetwork.egg-info/PKG-INFO
APNNetwork.egg-info/SOURCES.txt
APNNetwork.egg-info/dependency_links.txt
APNNetwork.egg-info/top_level.txt
APN_Net/__init__.py
APN_Net/netserver.py