Metadata-Version: 1.0
Name: APNNetwork
Version: 0.0.2
Summary: My English is bad,APN's coder in bilibili,if it has bug,then write email to me.
Home-page: UNKNOWN
Author: Yubadboy
Author-email: 2025677540@qq.com
License: UNKNOWN
Platform: UNKNOWN
